json_sett.py
json_sett-0.0.0.dist-info/LICENSE
json_sett-0.0.0.dist-info/METADATA
json_sett-0.0.0.dist-info/WHEEL
json_sett-0.0.0.dist-info/top_level.txt
json_sett-0.0.0.dist-info/RECORD
