Metadata-Version: 2.1
Name: json-sett
Version: 0.0.0
Summary: load and save settings from/ to a json file
Home-page: https://github.com/Schnilsibus/json_sett.git
Author: Nils Urbach
Author-email: ndu01u@gmail.com
License: MIT
Keywords: json,settings
Classifier: Development Status :: 3 - Alpha
Classifier: Intended Audience :: Developers
Classifier: License :: OSI Approved :: MIT License
Classifier: Operating System :: OS Independent
Classifier: Natural Language :: English
Classifier: Programming Language :: Python
License-File: LICENSE
Requires-Dist: json-convenience
